LICENSE
Makefile
README.rst
config/bitly.json
config/googl.json
config/lnk.json
config/tinyurl.json
docs/Makefile
docs/source/bitly.rst
docs/source/conf.py
docs/source/config.rst
docs/source/index.rst
docs/source/lnk.bitly.rst
docs/source/lnk.config.rst
docs/source/lnk.googl.rst
docs/source/lnk.rst
docs/source/lnk.tinyurl.rst
docs/source/modules.rst
lnk/__init__.py
lnk/abstract.py
lnk/beauty.py
lnk/cli.py
lnk/countries.py
lnk/errors.py
lnk/bitly/__init__.py
lnk/bitly/cli.py
lnk/bitly/command.py
lnk/bitly/history.py
lnk/bitly/info.py
lnk/bitly/key.py
lnk/bitly/link.py
lnk/bitly/stats.py
lnk/bitly/user.py
lnk/config/__init__.py
lnk/config/cli.py
lnk/config/configure.py
lnk/config/manager.py
lnk/googl/__init__.py
lnk/googl/cli.py
lnk/googl/command.py
lnk/googl/history.py
lnk/googl/info.py
lnk/googl/key.py
lnk/googl/link.py
lnk/googl/stats.py
lnk/tinyurl/__init__.py
lnk/tinyurl/cli.py
lnk/tinyurl/command.py
lnk/tinyurl/link.py
lnk-0.1.4.dist-info/DESCRIPTION.rst
lnk-0.1.4.dist-info/entry_points.txt
lnk-0.1.4.dist-info/METADATA
lnk-0.1.4.dist-info/metadata.json
lnk-0.1.4.dist-info/RECORD
lnk-0.1.4.dist-info/top_level.txt
lnk-0.1.4.dist-info/WHEEL
tests/__init__.py
tests/paths.py
tests/bitly/*REPL* [python].py
tests/bitly/__init__.py
tests/bitly/test_bitly_command.py
tests/bitly/test_bitly_history.py
tests/bitly/test_bitly_info.py
tests/bitly/test_bitly_key.py
tests/bitly/test_bitly_link.py
tests/bitly/test_bitly_stats.py
tests/bitly/test_bitly_user.py
tests/bitly/token
tests/config/__init__.py
tests/config/changed_command.json
tests/config/changed_manager.json
tests/config/test_command.json
tests/config/test_config_manager.py
tests/config/test_configure.py
tests/config/test_manager.json
tests/googl/.credentials
tests/googl/__init__.py
tests/googl/test_googl_command.py
tests/googl/test_googl_history.py
tests/googl/test_googl_info.py
tests/googl/test_googl_link.py
tests/googl/test_googl_stats.py
tests/lnk/__init__.py
tests/lnk/test.json
tests/lnk/test_lnk_abstract.py
tests/lnk/test_lnk_beauty.py
tests/lnk/test_lnk_errors.py
tests/tinyurl/test_tinyurl_command.py
tests/tinyurl/test_tinyurl_link.py
