Metadata-Version: 2.0
Name: lnk
Version: 0.1.4
Summary: A command-line URL-shortening client.
Home-page: https://github.com/goldsborough/lnk
Author: Peter Goldsborough
Author-email: petergoldsborough@hotmail.com
License: MIT
Keywords: lnk,url-shortening,bitly,googl,tinyurl
Platform: UNKNOWN
Classifier: Development Status :: 4 - Beta
Classifier: Intended Audience :: Developers
Classifier: Intended Audience :: End Users/Desktop
Classifier: Topic :: Internet
Classifier: Topic :: Desktop Environment
Classifier: License :: OSI Approved :: MIT License
Classifier: Programming Language :: Python
Classifier: Programming Language :: Python :: 2
Classifier: Programming Language :: Python :: 2.6
Classifier: Programming Language :: Python :: 2.7
Classifier: Programming Language :: Python :: 3
Classifier: Programming Language :: Python :: 3.2
Classifier: Programming Language :: Python :: 3.3
Classifier: Programming Language :: Python :: 3.4
Requires-Dist: click (==4.1)
Requires-Dist: coverage (==3.7.1)
Requires-Dist: ecstasy (==0.1.3)
Requires-Dist: google-api-python-client (==1.4.2)
Requires-Dist: pyperclip (==1.5.11)
Requires-Dist: requests (==2.7.0)
Requires-Dist: ordereddict (==1.1)
Requires-Dist: enum34 (==1.0.4)
